gradio_myfirstcomponent/__init__.py
gradio_myfirstcomponent/myfirstcomponent.py
gradio_myfirstcomponent/myfirstcomponent.pyi
gradio_myfirstcomponent/templates/component/Index-C50qCAiW.js
gradio_myfirstcomponent/templates/component/_basePickBy-CM8-Svbi.js
gradio_myfirstcomponent/templates/component/_baseUniq-B8xih7qU.js
gradio_myfirstcomponent/templates/component/arc-HKlWOjKU.js
gradio_myfirstcomponent/templates/component/architectureDiagram-IEHRJDOE-DQneAgsG.js
gradio_myfirstcomponent/templates/component/blockDiagram-JOT3LUYC-pVweua4T.js
gradio_myfirstcomponent/templates/component/c4Diagram-VJAJSXHY-DVKbTdjo.js
gradio_myfirstcomponent/templates/component/channel-ChNseWYf.js
gradio_myfirstcomponent/templates/component/chunk-4BMEZGHF-Bh-B5Lwv.js
gradio_myfirstcomponent/templates/component/chunk-A2AXSNBT-CviC1rmW.js
gradio_myfirstcomponent/templates/component/chunk-AEK57VVT-CF4M96Xy.js
gradio_myfirstcomponent/templates/component/chunk-D6G4REZN-BEfQf6lK.js
gradio_myfirstcomponent/templates/component/chunk-RZ5BOZE2-BB38CaaI.js
gradio_myfirstcomponent/templates/component/chunk-XZIHB7SX-BBk4jlR_.js
gradio_myfirstcomponent/templates/component/classDiagram-GIVACNV2-IvBuIiEK.js
gradio_myfirstcomponent/templates/component/classDiagram-v2-COTLJTTW-IvBuIiEK.js
gradio_myfirstcomponent/templates/component/clone-Bq3PAs9P.js
gradio_myfirstcomponent/templates/component/cytoscape.esm-C2cgT2B2.js
gradio_myfirstcomponent/templates/component/dagre-OKDRZEBW-CHuVHwlS.js
gradio_myfirstcomponent/templates/component/diagram-SSKATNLV-OVIgxZE7.js
gradio_myfirstcomponent/templates/component/diagram-VNBRO52H-bM4eFelG.js
gradio_myfirstcomponent/templates/component/erDiagram-Q7BY3M3F-C3l3yKNx.js
gradio_myfirstcomponent/templates/component/flowDiagram-4HSFHLVR-DdXThEK4.js
gradio_myfirstcomponent/templates/component/ganttDiagram-APWFNJXF-DNR0pAd8.js
gradio_myfirstcomponent/templates/component/gitGraphDiagram-7IBYFJ6S-BALbRRl1.js
gradio_myfirstcomponent/templates/component/graph-0i6sm4fb.js
gradio_myfirstcomponent-0.0.1.dist-info/METADATA
gradio_myfirstcomponent-0.0.1.dist-info/WHEEL
gradio_myfirstcomponent-0.0.1.dist-info/RECORD
